wraith.py
wraith-1.0.1.dist-info/LICENSE
wraith-1.0.1.dist-info/METADATA
wraith-1.0.1.dist-info/WHEEL
wraith-1.0.1.dist-info/top_level.txt
wraith-1.0.1.dist-info/RECORD
